peakrdl_busdecoder/__init__.py
peakrdl_busdecoder/__peakrdl__.py
peakrdl_busdecoder/decode_logic_gen.py
peakrdl_busdecoder/design_scanner.py
peakrdl_busdecoder/design_state.py
peakrdl_busdecoder/exporter.py
peakrdl_busdecoder/identifier_filter.py
peakrdl_busdecoder/listener.py
peakrdl_busdecoder/module_tmpl.sv
peakrdl_busdecoder/package_tmpl.sv
peakrdl_busdecoder/py.typed
peakrdl_busdecoder/struct_gen.py
peakrdl_busdecoder/sv_int.py
peakrdl_busdecoder/utils.py
peakrdl_busdecoder/validate_design.py
peakrdl_busdecoder/body/__init__.py
peakrdl_busdecoder/body/body.py
peakrdl_busdecoder/body/combinational_body.py
peakrdl_busdecoder/body/for_loop_body.py
peakrdl_busdecoder/body/if_body.py
peakrdl_busdecoder/body/struct_body.py
peakrdl_busdecoder/cpuif/__init__.py
peakrdl_busdecoder/cpuif/base_cpuif.py
peakrdl_busdecoder/cpuif/fanin_gen.py
peakrdl_busdecoder/cpuif/fanin_intermediate_gen.py
peakrdl_busdecoder/cpuif/fanout_gen.py
peakrdl_busdecoder/cpuif/interface.py
peakrdl_busdecoder/cpuif/apb3/__init__.py
peakrdl_busdecoder/cpuif/apb3/apb3_cpuif.py
peakrdl_busdecoder/cpuif/apb3/apb3_cpuif_flat.py
peakrdl_busdecoder/cpuif/apb3/apb3_interface.py
peakrdl_busdecoder/cpuif/apb3/apb3_tmpl.sv
peakrdl_busdecoder/cpuif/apb4/__init__.py
peakrdl_busdecoder/cpuif/apb4/apb4_cpuif.py
peakrdl_busdecoder/cpuif/apb4/apb4_cpuif_flat.py
peakrdl_busdecoder/cpuif/apb4/apb4_interface.py
peakrdl_busdecoder/cpuif/apb4/apb4_tmpl.sv
peakrdl_busdecoder/cpuif/axi4lite/__init__.py
peakrdl_busdecoder/cpuif/axi4lite/axi4_lite_cpuif.py
peakrdl_busdecoder/cpuif/axi4lite/axi4_lite_cpuif_flat.py
peakrdl_busdecoder/cpuif/axi4lite/axi4_lite_interface.py
peakrdl_busdecoder/cpuif/axi4lite/axi4_lite_tmpl.sv
peakrdl_busdecoder/udps/__init__.py
peakrdl_busdecoder-0.6.5.dist-info/licenses/LICENSE
peakrdl_busdecoder-0.6.5.dist-info/METADATA
peakrdl_busdecoder-0.6.5.dist-info/WHEEL
peakrdl_busdecoder-0.6.5.dist-info/entry_points.txt
peakrdl_busdecoder-0.6.5.dist-info/top_level.txt
peakrdl_busdecoder-0.6.5.dist-info/RECORD
