Metadata-Version: 2.4
Name: peakrdl-busdecoder
Version: 0.6.5
Summary: Generate a SystemVerilog bus decoder from SystemRDL for splitting CPU interfaces to multiple sub-address spaces
Author: Arnav Sacheti
License: LGPLv3
Project-URL: Source, https://github.com/arnavsacheti/PeakRDL-BusDecoder
Project-URL: Tracker, https://github.com/arnavsacheti/PeakRDL-BusDecoder/issues
Project-URL: Changelog, https://github.com/arnavsacheti/PeakRDL-BusDecoder/releases
Project-URL: Documentation, https://peakrdl-busdecoder.readthedocs.io/
Keywords: SystemRDL,PeakRDL,bus decoder,address decoder,hierarchical addressing,compiler,tool,registers,generator,Verilog,SystemVerilog,register abstraction layer,FPGA,ASIC
Classifier: Development Status :: 5 - Production/Stable
Classifier: Programming Language :: Python
Classifier: Programming Language :: Python :: 3
Classifier: Programming Language :: Python :: 3 :: Only
Classifier: Intended Audience :: Developers
Classifier: License :: OSI Approved :: GNU Lesser General Public License v3 (LGPLv3)
Classifier: Operating System :: OS Independent
Classifier: Topic :: Scientific/Engineering :: Electronic Design Automation (EDA)
Requires-Python: >=3.10
License-File: LICENSE
Requires-Dist: jinja2~=3.1
Requires-Dist: systemrdl-compiler~=1.30
Provides-Extra: cli
Requires-Dist: peakrdl-cli>=1.2.3; extra == "cli"
Dynamic: license-file
